LICENSE.txt
MANIFEST.in
README.rst
pyproject.toml
setup.py
tutor_mfe.egg-info/PKG-INFO
tutor_mfe.egg-info/SOURCES.txt
tutor_mfe.egg-info/dependency_links.txt
tutor_mfe.egg-info/entry_points.txt
tutor_mfe.egg-info/requires.txt
tutor_mfe.egg-info/top_level.txt
tutormfe/__about__.py
tutormfe/__init__.py
tutormfe/hooks.py
tutormfe/plugin.py
tutormfe/patches/.gitignore
tutormfe/patches/caddyfile
tutormfe/patches/k8s-deployments
tutormfe/patches/k8s-services
tutormfe/patches/kustomization-configmapgenerator
tutormfe/patches/local-docker-compose-dev-services
tutormfe/patches/local-docker-compose-services
tutormfe/patches/openedx-cms-development-settings
tutormfe/patches/openedx-cms-production-settings
tutormfe/patches/openedx-lms-common-settings
tutormfe/patches/openedx-lms-development-settings
tutormfe/patches/openedx-lms-production-settings
tutormfe/templates/mfe/apps/.gitignore
tutormfe/templates/mfe/apps/mfe/Caddyfile
tutormfe/templates/mfe/apps/mfe/webpack.dev-tutor.config.js
tutormfe/templates/mfe/build/.gitignore
tutormfe/templates/mfe/build/mfe/Dockerfile
tutormfe/templates/mfe/build/mfe/env.config.jsx
tutormfe/templates/mfe/tasks/.gitignore
tutormfe/templates/mfe/tasks/lms/init